LICENSE
MANIFEST.in
README.rst
setup.py
bin/mcinspect
memcacheinspector/__init__.py
memcacheinspector.egg-info/PKG-INFO
memcacheinspector.egg-info/SOURCES.txt
memcacheinspector.egg-info/dependency_links.txt
memcacheinspector.egg-info/requires.txt
memcacheinspector.egg-info/top_level.txt