Metadata-Version: 1.0
Name: memcacheinspector
Version: 0.2.0
Summary: Memcache Inspection Module and Command-Line Utility
Home-page: https://bitbucket.org/jayclassless/memcacheinspector
Author: Jason Simeone
Author-email: jay@classless.net
License: MIT
Keywords: memcache memcached inspector list dump search grep
Platform: UNKNOWN
Classifier: Development Status :: 4 - Beta
Classifier: Environment :: Console
Classifier: Intended Audience :: Developers
Classifier: Intended Audience :: System Administrators
Classifier: Natural Language :: English
Classifier: Programming Language :: Python
Classifier: Topic :: Software Development :: Libraries :: Python Modules
Classifier: License :: OSI Approved :: MIT License
